pyflow/__init__.py
pyflow/__main__.py
pyflow/logging.py
pyflow/blocks/__init__.py
pyflow/blocks/block.py
pyflow/blocks/codeblock.py
pyflow/blocks/containerblock.py
pyflow/blocks/drawingblock.py
pyflow/blocks/executableblock.py
pyflow/blocks/markdownblock.py
pyflow/blocks/mdeditor.py
pyflow/blocks/pyeditor.py
pyflow/blocks/sliderblock.py
pyflow/blocks/blockfiles/empty.pfb
pyflow/blocks/blockfiles/markdown.pfb
pyflow/blocks/widgets/__init__.py
pyflow/blocks/widgets/blocksizegrip.py
pyflow/blocks/widgets/blocksplitter.py
pyflow/blocks/widgets/blocktitle.py
pyflow/core/__init__.py
pyflow/core/add_button.py
pyflow/core/edge.py
pyflow/core/editor.py
pyflow/core/executable.py
pyflow/core/history.py
pyflow/core/kernel.py
pyflow/core/serializable.py
pyflow/core/socket.py
pyflow/core/worker.py
pyflow/graphics/__init__.py
pyflow/graphics/theme.py
pyflow/graphics/theme_manager.py
pyflow/graphics/view.py
pyflow/graphics/widget.py
pyflow/graphics/window.py
pyflow/qss/__init__.py
pyflow/qss/dark_resources.py
pyflow/qss/pyflow.qss
pyflow/qss/pyflow_dark.qss
pyflow/scene/__init__.py
pyflow/scene/clipboard.py
pyflow/scene/from_ipynb_conversion.py
pyflow/scene/history.py
pyflow/scene/ipynb_conversion_constants.py
pyflow/scene/scene.py
pyflow/scene/to_ipynb_conversion.py
pyflow/themes/default.theme
pyflow/themes/monokai.theme
byc_pyflow-1.0.0.dist-info/LICENSE
byc_pyflow-1.0.0.dist-info/METADATA
byc_pyflow-1.0.0.dist-info/WHEEL
byc_pyflow-1.0.0.dist-info/top_level.txt
byc_pyflow-1.0.0.dist-info/RECORD
