Metadata-Version: 2.1
Name: byc-pyflow
Version: 1.0.0
Summary: An open-source tool for modular visual programing in python
Home-page: https://github.com/Bycelium/PyFlow
Author: Bycelium
Author-email: mathis.federico@bycelium.com
License: GPLv3
Platform: UNKNOWN
Classifier: Programming Language :: Python :: 3
Classifier: License :: OSI Approved :: GNU General Public License v3 (GPLv3)
Classifier: Operating System :: OS Independent
Requires-Python: >=3.7
License-File: LICENSE
Requires-Dist: pyqt5 (>=5.15.4)
Requires-Dist: qscintilla (>=2.13.0)
Requires-Dist: Ipython (>=7.27.0)
Requires-Dist: tornado (>=6.0)
Requires-Dist: jupyter-client (>=7.0.6)
Requires-Dist: ipykernel (>=6.5.0)
Requires-Dist: ansi2html (>=1.6.0)
Requires-Dist: markdown (>=3.3.6)
Requires-Dist: pyqtwebengine (>=5.15.5)
Requires-Dist: colorama (>=0.4.4)
